py_perceptabat_cv/__init__.py
py_perceptabat_cv/py_perceptabat_cv.py
py_perceptabat_cv-1.2.2.dist-info/LICENSE AGREEMENT (PERPETUAL AND TERM).PDF
py_perceptabat_cv-1.2.2.dist-info/LICENSE.txt
py_perceptabat_cv-1.2.2.dist-info/METADATA
py_perceptabat_cv-1.2.2.dist-info/WHEEL
py_perceptabat_cv-1.2.2.dist-info/entry_points.txt
py_perceptabat_cv-1.2.2.dist-info/top_level.txt
py_perceptabat_cv-1.2.2.dist-info/RECORD
